wechat/__init__.py
wechat/apps.py
wechat/base.py
wechat/message.py
wechat/payment.py
wechat/payment3.py
wechat/tests.py
wechat/wxa.py
wechat/wxb.py
django_wechat_base-2.1.1.dist-info/LICENSE
django_wechat_base-2.1.1.dist-info/METADATA
django_wechat_base-2.1.1.dist-info/WHEEL
django_wechat_base-2.1.1.dist-info/top_level.txt
django_wechat_base-2.1.1.dist-info/RECORD
